<?xml version="1.0" encoding="utf-8"?><LanguageData> 	<!--1541243129_190628_Rimperion-->	<NegativeRecoil_W_HG.label>네거티브 리코일</NegativeRecoil_W_HG.label>	<NegativeRecoil_W_HG.description>모든 사격 정확도가 증가합니다.</NegativeRecoil_W_HG.description>	<NegativeRecoil_P_HG.label>네거티브 리코일</NegativeRecoil_P_HG.label>	<NegativeRecoil_P_HG.description>모든 사격 정확도가 증가합니다.</NegativeRecoil_P_HG.description>	<NegativeRecoil_W_SMG.label>네거티브 리코일</NegativeRecoil_W_SMG.label>	<NegativeRecoil_W_SMG.description>모든 사격 정확도가 증가합니다.</NegativeRecoil_W_SMG.description>	<NegativeRecoil_P_SMG.label>네거티브 리코일</NegativeRecoil_P_SMG.label>	<NegativeRecoil_P_SMG.description>모든 사격 정확도가 증가합니다.</NegativeRecoil_P_SMG.description>	<NegativeRecoil_W_AR.label>네거티브 리코일</NegativeRecoil_W_AR.label>	<NegativeRecoil_W_AR.description>모든 사격 정확도가 증가합니다.</NegativeRecoil_W_AR.description>	<NegativeRecoil_P_AR.label>네거티브 리코일</NegativeRecoil_P_AR.label>	<NegativeRecoil_P_AR.description>모든 사격 정확도가 증가합니다.</NegativeRecoil_P_AR.description>	<NegativeRecoil_W_RF.label>네거티브 리코일</NegativeRecoil_W_RF.label>	<NegativeRecoil_W_RF.description>모든 사격 정확도가 증가합니다.</NegativeRecoil_W_RF.description>	<NegativeRecoil_P_RF.label>네거티브 리코일</NegativeRecoil_P_RF.label>	<NegativeRecoil_P_RF.description>모든 사격 정확도가 증가합니다.</NegativeRecoil_P_RF.description>	<NegativeRecoil_W_SG.label>네거티브 리코일</NegativeRecoil_W_SG.label>	<NegativeRecoil_W_SG.description>모든 사격 정확도가 증가합니다.</NegativeRecoil_W_SG.description>	<NegativeRecoil_P_SG.label>네거티브 리코일</NegativeRecoil_P_SG.label>	<NegativeRecoil_P_SG.description>모든 사격 정확도가 증가합니다.</NegativeRecoil_P_SG.description>	<NegativeRecoil_W_LMG.label>네거티브 리코일</NegativeRecoil_W_LMG.label>	<NegativeRecoil_W_LMG.description>모든 사격 정확도가 증가합니다.</NegativeRecoil_W_LMG.description>	<NegativeRecoil_P_LMG.label>네거티브 리코일</NegativeRecoil_P_LMG.label>	<NegativeRecoil_P_LMG.description>모든 사격 정확도가 증가합니다.</NegativeRecoil_P_LMG.description></LanguageData>