<?xml version="1.0" encoding="utf-8"?>
<LanguageData>

  <AttendedFuneral.stages.0.label>장례식에 참석함</AttendedFuneral.stages.0.label>
  <AttendedFuneral.stages.0.description>정착민의 장례식에 참석했어. 기분이 좀 나아진것 같애.</AttendedFuneral.stages.0.description>

  <WitnessedDeathAllyBleedingHeart.stages.0.label>동료의 죽음을 목격함</WitnessedDeathAllyBleedingHeart.stages.0.label>
  <WitnessedDeathAllyBleedingHeart.stages.0.description>동료가 죽었어. 이렇게 죽다니 믿을 수가 없어. 다신 웃으며 대화를 나눌 수 없다니 너무 슬퍼.</WitnessedDeathAllyBleedingHeart.stages.0.description>

  <WitnessedDeathNonAllyBleedingHeart.stages.0.label>외부인의 죽음을 목격함</WitnessedDeathNonAllyBleedingHeart.stages.0.label>
  <WitnessedDeathNonAllyBleedingHeart.stages.0.description>누군가 죽는 걸 봤어. 눈동자에 불이 켜져있었는데, 마치 촛불이 꺼지는 것처럼 사라지더군.</WitnessedDeathNonAllyBleedingHeart.stages.0.description>

  <KnowGuestExecutedBleedingHeart.stages.0.label>정당한 처형</KnowGuestExecutedBleedingHeart.stages.0.label>
  <KnowGuestExecutedBleedingHeart.stages.0.description>죄를 지은 사람이 처형당했어. 정당한 일이라고해도 생명을 잃는다는건 슬픈 일이야.</KnowGuestExecutedBleedingHeart.stages.0.description>
  <KnowGuestExecutedBleedingHeart.stages.1.label>안락사</KnowGuestExecutedBleedingHeart.stages.1.label>
  <KnowGuestExecutedBleedingHeart.stages.1.description>누군가 안락사되었어. 인도적이긴 하지만 여전히 가슴이 아파.</KnowGuestExecutedBleedingHeart.stages.1.description>
  <KnowGuestExecutedBleedingHeart.stages.2.label>처형</KnowGuestExecutedBleedingHeart.stages.2.label>
  <KnowGuestExecutedBleedingHeart.stages.2.description>누군가 냉혹하게 처형을 당했어. 내 눈으로 보고도 믿을수가 없군!</KnowGuestExecutedBleedingHeart.stages.2.description>
  <KnowGuestExecutedBleedingHeart.stages.3.label>장기 적출로 사망</KnowGuestExecutedBleedingHeart.stages.3.label>
  <KnowGuestExecutedBleedingHeart.stages.3.description>누군가의 장기를 적출하려다 죽어버렸어. 아직도 생생한게 너무 끔찍해!</KnowGuestExecutedBleedingHeart.stages.3.description>

  <KnowColonistExecutedBleedingHeart.stages.0.label>정당한 처형 (정착민)</KnowColonistExecutedBleedingHeart.stages.0.label>
  <KnowColonistExecutedBleedingHeart.stages.0.description>죄를 지은 정착민이 처형당했어. 정당한 일이라고해도 생명을 잃는다는건 슬픈 일이야.</KnowColonistExecutedBleedingHeart.stages.0.description>
  <KnowColonistExecutedBleedingHeart.stages.1.label>안락사 (정착민)</KnowColonistExecutedBleedingHeart.stages.1.label>
  <KnowColonistExecutedBleedingHeart.stages.1.description>정착민이 안락사되었어. 인도적이긴 하지만 여전히 가슴이 아파.</KnowColonistExecutedBleedingHeart.stages.1.description>
  <KnowColonistExecutedBleedingHeart.stages.2.label>처형 (정착민)</KnowColonistExecutedBleedingHeart.stages.2.label>
  <KnowColonistExecutedBleedingHeart.stages.2.description>정착민이 냉혹하게 처형을 당했어. 내 눈으로 보고도 믿을수가 없군!</KnowColonistExecutedBleedingHeart.stages.2.description>
  <KnowColonistExecutedBleedingHeart.stages.3.label>장기적출로 사망 (정착민)</KnowColonistExecutedBleedingHeart.stages.3.label>
  <KnowColonistExecutedBleedingHeart.stages.3.description>정착민의 장기를 적출하려다 죽어버렸어. 아직도 생생한게 너무 끔찍해!</KnowColonistExecutedBleedingHeart.stages.3.description>

  <KnowPrisonerDiedInnocentBleedingHeart.stages.0.label>결백한 수감자 사망</KnowPrisonerDiedInnocentBleedingHeart.stages.0.label>
  <KnowPrisonerDiedInnocentBleedingHeart.stages.0.description>무죄임에도 불구하고 수감자 한 명이 죽었어. 우린 저들을 챙겨줬어야 해. 그 사람이 죽길 원했다고 해도, 야만적으로 방치하지 말고 규칙에 맞는 처형을 했어야 됐다고.</KnowPrisonerDiedInnocentBleedingHeart.stages.0.description>

  <KnowColonistDiedBleedingHeart.stages.0.label>정착민 사망</KnowColonistDiedBleedingHeart.stages.0.label>
  <KnowColonistDiedBleedingHeart.stages.0.description>동료가 죽었어. 이렇게 내버려둬선 안돼...</KnowColonistDiedBleedingHeart.stages.0.description>

</LanguageData>